streetrace/__init__.py
streetrace/agents/__init__.py
streetrace/agents/agent_manager.py
streetrace/agents/base_agent_loader.py
streetrace/agents/code_reviewer/README.md
streetrace/agents/code_reviewer/__init__.py
streetrace/agents/code_reviewer/agent.py
streetrace/agents/coder/README.md
streetrace/agents/coder/__init__.py
streetrace/agents/coder/agent.py
streetrace/agents/config_inspector/README.md
streetrace/agents/config_inspector/__init__.py
streetrace/agents/config_inspector/agent.py
streetrace/agents/example/README.md
streetrace/agents/example/__init__.py
streetrace/agents/example/agent.py
streetrace/agents/py_agent_loader.py
streetrace/agents/street_race_agent.py
streetrace/agents/street_race_agent_card.py
streetrace/agents/yaml_agent.py
streetrace/agents/yaml_agent_builder.py
streetrace/agents/yaml_agent_loader.py
streetrace/agents/yaml_models.py
streetrace/app.py
streetrace/app_state.py
streetrace/args.py
streetrace/bash_handler.py
streetrace/commands/__init__.py
streetrace/commands/base_command.py
streetrace/commands/command_executor.py
streetrace/commands/definitions/__init__.py
streetrace/commands/definitions/compact_command.py
streetrace/commands/definitions/exit_command.py
streetrace/commands/definitions/help_command.py
streetrace/commands/definitions/history_command.py
streetrace/commands/definitions/reset_command.py
streetrace/costs.py
streetrace/input_handler.py
streetrace/list_agents.py
streetrace/llm/__init__.py
streetrace/llm/lite_llm_client.py
streetrace/llm/llm_interface.py
streetrace/llm/model_factory.py
streetrace/log.py
streetrace/main.py
streetrace/messages.py
streetrace/output_file_handler.py
streetrace/preload_deps.py
streetrace/prompt_processor.py
streetrace/py.typed
streetrace/session/__init__.py
streetrace/session/json_serializer.py
streetrace/session/session_manager.py
streetrace/session/session_service.py
streetrace/session_md.py
streetrace/system_context.py
streetrace/terminal_session.py
streetrace/tools/__init__.py
streetrace-0.1.21.dist-info/METADATA
streetrace-0.1.21.dist-info/WHEEL
streetrace-0.1.21.dist-info/entry_points.txt
streetrace-0.1.21.dist-info/licenses/LICENSE
streetrace-0.1.21.dist-info/RECORD
