Metadata-Version: 2.4
Name: streetrace
Version: 0.1.21
Summary: StreetRace is an agentic AI coding partner designed to help engineers leverage AI capabilities directly from the command line to create software.
License: MIT License
License-File: LICENSE
Author: Street Race Team
Requires-Python: >=3.12,<4.0
Classifier: License :: Other/Proprietary License
Classifier: Programming Language :: Python :: 3
Classifier: Programming Language :: Python :: 3.12
Classifier: Programming Language :: Python :: 3.13
Classifier: Programming Language :: Python :: 3.14
Requires-Dist: a2a-sdk (>=0.2.4,<0.3.0)
Requires-Dist: anthropic (>=0.54.0,<0.55.0)
Requires-Dist: bashlex (>=0.18,<0.19)
Requires-Dist: boto3 (>=1.28.57,<2.0.0)
Requires-Dist: botocore (>=1.29.0,<2.0.0)
Requires-Dist: deprecated (>=1.2.18,<2.0.0)
Requires-Dist: dotenv (>=0.9.9,<0.10.0)
Requires-Dist: google-adk (>=1.3.0,<2.0.0)
Requires-Dist: google-genai (>=1.12.1,<2.0.0)
Requires-Dist: httpx (>=0.28.1,<0.29.0)
Requires-Dist: litellm (>=1.67.5,<2.0.0)
Requires-Dist: marko (>=2.1.3,<3.0.0)
Requires-Dist: mcp (>=1.7.1,<2.0.0)
Requires-Dist: ollama (>=0.5.1,<0.6.0)
Requires-Dist: openai (>=1.76.0,<2.0.0)
Requires-Dist: pathspec (>=0.12.1,<0.13.0)
Requires-Dist: prompt-toolkit (>=3.0.51,<4.0.0)
Requires-Dist: pydantic (>=2.11.7,<3.0.0)
Requires-Dist: pypubsub (>=4.0.3,<5.0.0)
Requires-Dist: pyyaml (>=6.0.1,<7.0.0)
Requires-Dist: rich (>=14.0.0,<15.0.0)
Requires-Dist: tenacity (>=9.1.2,<10.0.0)
Requires-Dist: typed-argparse (>=0.3.1,<0.4.0)
Requires-Dist: tzlocal (>=5.3.1,<6.0.0)
